LICENSE
README.md
sample-config.toml
asciiquarium_redux/__init__.py
asciiquarium_redux/__main__.py
asciiquarium_redux/app.py
asciiquarium_redux/constants.py
asciiquarium_redux/protocols.py
asciiquarium_redux/runner.py
asciiquarium_redux/screen_compat.py
asciiquarium_redux/web_server.py
asciiquarium_redux/ai/__init__.py
asciiquarium_redux/ai/brain.py
asciiquarium_redux/ai/noise.py
asciiquarium_redux/ai/steering.py
asciiquarium_redux/ai/utility.py
asciiquarium_redux/ai/vector.py
asciiquarium_redux/backend/__init__.py
asciiquarium_redux/backend/factory.py
asciiquarium_redux/backend/shared.py
asciiquarium_redux/backend/term/__init__.py
asciiquarium_redux/backend/term/term_backends.py
asciiquarium_redux/backend/tk/__init__.py
asciiquarium_redux/backend/tk/runner.py
asciiquarium_redux/backend/web/__init__.py
asciiquarium_redux/backend/web/web_backend.py
asciiquarium_redux/backend/web/web_screen.py
asciiquarium_redux/entities/base.py
asciiquarium_redux/entities/core.py
asciiquarium_redux/entities/environment.py
asciiquarium_redux/entities/specials.py
asciiquarium_redux/entities/core/__init__.py
asciiquarium_redux/entities/core/behavior.py
asciiquarium_redux/entities/core/bubble.py
asciiquarium_redux/entities/core/fish.py
asciiquarium_redux/entities/core/fish_assets.py
asciiquarium_redux/entities/core/seaweed.py
asciiquarium_redux/entities/core/species.py
asciiquarium_redux/entities/core/splat.py
asciiquarium_redux/entities/specials/__init__.py
asciiquarium_redux/entities/specials/big_fish.py
asciiquarium_redux/entities/specials/crab.py
asciiquarium_redux/entities/specials/dolphins.py
asciiquarium_redux/entities/specials/ducks.py
asciiquarium_redux/entities/specials/fish_food.py
asciiquarium_redux/entities/specials/fishhook.py
asciiquarium_redux/entities/specials/monster.py
asciiquarium_redux/entities/specials/scuba_diver.py
asciiquarium_redux/entities/specials/shark.py
asciiquarium_redux/entities/specials/ship.py
asciiquarium_redux/entities/specials/submarine.py
asciiquarium_redux-1.5.0.dist-info/METADATA
asciiquarium_redux-1.5.0.dist-info/WHEEL
asciiquarium_redux-1.5.0.dist-info/entry_points.txt
asciiquarium_redux-1.5.0.dist-info/licenses/LICENSE
asciiquarium_redux-1.5.0.dist-info/licenses/LICENSE.md
asciiquarium_redux-1.5.0.dist-info/RECORD
