Metadata-Version: 2.4
Name: asciiquarium-redux
Version: 1.5.0
Summary: A Python port of Asciiquarium with asciimatics
Project-URL: Homepage, https://github.com/cognitivegears/asciiquarium_redux
Project-URL: Source, https://github.com/cognitivegears/asciiquarium_redux
Project-URL: Issues, https://github.com/cognitivegears/asciiquarium_redux/issues
Author: cognitivegears
License: GPL-2.0-or-later
License-File: LICENSE
License-File: LICENSE.md
Keywords: aquarium,ascii-art,asciimatics,asciiquarium,terminal
Classifier: Environment :: Console
Classifier: License :: OSI Approved :: GNU General Public License v2 or later (GPLv2+)
Classifier: Programming Language :: Python :: 3
Classifier: Programming Language :: Python :: 3 :: Only
Classifier: Programming Language :: Python :: 3.11
Classifier: Programming Language :: Python :: 3.12
Classifier: Programming Language :: Python :: 3.13
Classifier: Programming Language :: Python :: 3.14
Classifier: Topic :: Artistic Software
Classifier: Topic :: Games/Entertainment :: Simulation
Requires-Python: >=3.11
Requires-Dist: asciimatics>=1.15.0
